punting/__init__.py
punting/onedim/__init__.py
punting/onedim/onenormalization.py
punting/onedim/onescratching.py
punting/twodim/__init__.py
punting/twodim/twodimensions.py
punting/twodim/twoharville.py
punting/twodim/twonormalization.py
punting/twodim/twoscratching.py
punting/twodim/twosynthetic.py
punting-0.0.4.dist-info/LICENSE
punting-0.0.4.dist-info/METADATA
punting-0.0.4.dist-info/WHEEL
punting-0.0.4.dist-info/entry_points.txt
punting-0.0.4.dist-info/top_level.txt
punting-0.0.4.dist-info/RECORD
